lines_methods/__init__.py
lines_methods/lines_methods.py
lines_methods-0.0.9.dist-info/LICENSE
lines_methods-0.0.9.dist-info/METADATA
lines_methods-0.0.9.dist-info/WHEEL
lines_methods-0.0.9.dist-info/top_level.txt
lines_methods-0.0.9.dist-info/RECORD
