Metadata-Version: 2.1
Name: lines-methods
Version: 0.0.9
Summary: This is the simplest module for quick work with 2D vectors
Home-page: https://github.com/UgryumovAV
Author: UgryumovAV
Author-email: ugriumov2102@gmail.com
Project-URL: GitHub, https://github.com/UgryumovAV/lines_methods/
Keywords: lines methods
Classifier: Programming Language :: Python :: 3.11
Classifier: License :: OSI Approved :: MIT License
Classifier: Operating System :: OS Independent
Requires-Python: >=3.8
License-File: LICENSE
